{
  "links": [
    {
      "id": 1,
      "author": {
        "username": "nan-noo",
        "imageUrl": "https://picsum.photos/id/50/200/300",
        "profileUrl": "github.com/greenlawn",
        "id": 2
      },
      "linkUrl": "https://naver.com",
      "description": "네이버 홈",
      "createdDate": "2022-08-13",
      "lastModifiedDate": "2022-08-13"
    },
    {
      "id": 2,
      "author": {
        "username": "nan-noo",
        "imageUrl": "https://picsum.photos/id/50/200/300",
        "profileUrl": "github.com/greenlawn",
        "id": 2
      },
      "linkUrl": "https://www.npmjs.com/package/he",
      "description": "이것도 테스트해보자!",
      "createdDate": "2022-08-13",
      "lastModifiedDate": "2022-08-13"
    }
  ]
}
